pygoogletranslation/__init__.py
pygoogletranslation/constants.py
pygoogletranslation/gauthtoken.py
pygoogletranslation/models.py
pygoogletranslation/translate.py
pygoogletranslation/urls.py
pygoogletranslation/utils.py
pygoogletranslation-2.0.4.dist-info/METADATA
pygoogletranslation-2.0.4.dist-info/WHEEL
pygoogletranslation-2.0.4.dist-info/top_level.txt
pygoogletranslation-2.0.4.dist-info/RECORD
